lisaai/__init__.py
lisaai/__main__.py
lisaai/api.py
lisaai/checkpoint.py
lisaai/cli.py
lisaai/inspector.py
lisaai/repair.py
lisaai/runtime.py
lisaai/training.py
lisaai-0.1.0.dist-info/METADATA
lisaai-0.1.0.dist-info/WHEEL
lisaai-0.1.0.dist-info/entry_points.txt
lisaai-0.1.0.dist-info/top_level.txt
lisaai-0.1.0.dist-info/RECORD
