Metadata-Version: 2.4
Name: lisaai
Version: 0.1.0
Summary: High-level APIs and training utilities for the LISA Vision+Audio model
Author-email: LISA Team <lisateam@gmail.com>
License-Expression: Apache-2.0
Project-URL: homepage, https://lisaai.com/lisa
Requires-Python: >=3.9
Requires-Dist: torch
Requires-Dist: safetensors
